topdog_simple/__init__.py
topdog_simple/config.py
topdog_simple/history_compressor.py
topdog_simple/llmutil.py
topdog_simple/prompt_strategies.py
topdog_simple/prompts.py
topdog_simple/response_formatter.py
topdog_simple/start.py
topdog_simple/strategy_metrics.py
topdog_simple-0.5.0.dist-info/METADATA
topdog_simple-0.5.0.dist-info/WHEEL
topdog_simple-0.5.0.dist-info/entry_points.txt
topdog_simple-0.5.0.dist-info/top_level.txt
topdog_simple-0.5.0.dist-info/RECORD
