Metadata-Version: 2.4
Name: topdog-simple
Version: 0.5.0
Summary: Infinite loop driver for Claude Code with persistent context
Project-URL: Homepage, https://github.com/yourusername/topdog-simple
Project-URL: Repository, https://github.com/yourusername/topdog-simple
Classifier: Development Status :: 3 - Alpha
Classifier: Intended Audience :: Developers
Classifier: License :: OSI Approved :: MIT License
Classifier: Programming Language :: Python :: 3
Classifier: Programming Language :: Python :: 3.7
Classifier: Programming Language :: Python :: 3.8
Classifier: Programming Language :: Python :: 3.9
Classifier: Programming Language :: Python :: 3.10
Classifier: Programming Language :: Python :: 3.11
Requires-Python: >=3.7
Requires-Dist: anyio>=4.0.0
Requires-Dist: claude-code-sdk
